simplecalc/__init__.py
simplecalc/calculator.py
SimplePYCalc-0.1.0.dist-info/LICENSE
SimplePYCalc-0.1.0.dist-info/METADATA
SimplePYCalc-0.1.0.dist-info/WHEEL
SimplePYCalc-0.1.0.dist-info/top_level.txt
SimplePYCalc-0.1.0.dist-info/RECORD
